{
 "actions": [],
 "allow_rename": 1,
 "creation": "2026-02-12 07:44:43.024107",
 "default_view": "Calendar",
 "doctype": "DocType",
 "engine": "InnoDB",
 "field_order": [
  "guest_details_tab",
  "guest",
  "personal_details_section",
  "full_name",
  "column_break_hzor",
  "date_of_birth",
  "column_break_kshj",
  "company",
  "contact_details_section",
  "email_address",
  "city",
  "address_line_1",
  "column_break_gcyq",
  "phone_number",
  "state",
  "address_line_2",
  "column_break_ulel",
  "country",
  "postal_code",
  "section_break_jmqu",
  "guest_id_type",
  "column_break_imij",
  "id_number",
  "stay_and_rent_details_tab",
  "status_section",
  "status",
  "cancellation_reason",
  "hotel_stay",
  "column_break_status",
  "color",
  "cancellation_number",
  "proforma_invoice",
  "section_break_amte",
  "check_in_date",
  "check_in_time",
  "column_break_quex",
  "check_out_date",
  "check_out_time",
  "column_break_nzjo",
  "days",
  "no_of_rooms",
  "stay_details_section",
  "room_type",
  "room",
  "floor",
  "building",
  "column_break_bxqg",
  "market_segment",
  "column_break_rxah",
  "business_source_category",
  "requests_section",
  "special_requests",
  "comments",
  "column_break_requests",
  "eta",
  "turndown_requested",
  "turndown_reason",
  "no_post",
  "rate_details_tab",
  "adults",
  "column_break_ytyy",
  "children",
  "section_break_hxvt",
  "rate_lines",
  "section_break_totals",
  "total_charges",
  "column_break_saln",
  "tax",
  "column_break_zbxj",
  "total_rental",
  "section_break_tnrc",
  "deposit_received",
  "deposit",
  "cancellation_fee",
  "guarantee_and_payment_tab",
  "guarantee_section",
  "guarantee_type",
  "column_break_guarantee",
  "payment_method",
  "section_break_zons",
  "credit_card_type",
  "column_break_walv",
  "credit_card_last4",
  "column_break_mvqd",
  "card_expiry",
  "section_break_gufu",
  "guest_identification",
  "cheque_number",
  "column_break_dtml",
  "bank_name",
  "cheque_amount",
  "column_break_zcsq",
  "bank_account_no",
  "date_of_the_cheque",
  "section_break_ndhg",
  "customer_id",
  "amount",
  "confirmation_email_sent",
  "amended_from"
 ],
 "fields": [
  {
   "fieldname": "stay_and_rent_details_tab",
   "fieldtype": "Tab Break",
   "label": "Stay Details"
  },
  {
   "fieldname": "check_in_date",
   "fieldtype": "Date",
   "in_list_view": 1,
   "label": "Check In Date",
   "reqd": 1
  },
  {
   "fieldname": "check_in_time",
   "fieldtype": "Time",
   "label": "Check In Time"
  },
  {
   "fieldname": "column_break_quex",
   "fieldtype": "Column Break"
  },
  {
   "fieldname": "check_out_date",
   "fieldtype": "Date",
   "in_list_view": 1,
   "label": "Check Out Date",
   "reqd": 1
  },
  {
   "fieldname": "check_out_time",
   "fieldtype": "Time",
   "label": "Check Out Time"
  },
  {
   "fieldname": "column_break_nzjo",
   "fieldtype": "Column Break"
  },
  {
   "fieldname": "days",
   "fieldtype": "Int",
   "label": "Days",
   "read_only": 1
  },
  {
   "default": "1",
   "fieldname": "no_of_rooms",
   "fieldtype": "Int",
   "label": "No. of Rooms"
  },
  {
   "fieldname": "stay_details_section",
   "fieldtype": "Section Break",
   "label": "Stay Details"
  },
  {
   "fieldname": "room_type",
   "fieldtype": "Link",
   "in_list_view": 1,
   "label": "Room Type",
   "options": "Room Type"
  },
  {
   "fieldname": "room",
   "fieldtype": "Link",
   "label": "Room No.",
   "options": "Room"
  },
  {
   "fieldname": "column_break_bxqg",
   "fieldtype": "Column Break"
  },
  {
   "fetch_from": "room.building",
   "fieldname": "building",
   "fieldtype": "Data",
   "label": "Building",
   "read_only": 1
  },
  {
   "fetch_from": "room.floor",
   "fieldname": "floor",
   "fieldtype": "Data",
   "label": "Floor",
   "read_only": 1
  },
  {
   "default": "1",
   "fieldname": "adults",
   "fieldtype": "Int",
   "label": "Adults"
  },
  {
   "default": "0",
   "fieldname": "children",
   "fieldtype": "Int",
   "label": "Children"
  },
  {
   "fieldname": "market_segment",
   "fieldtype": "Link",
   "label": "Market Segment",
   "options": "Hotel Market Segment"
  },
  {
   "fieldname": "business_source_category",
   "fieldtype": "Link",
   "label": "Business Source",
   "options": "Business Source Category"
  },
  {
   "fieldname": "section_break_hxvt",
   "fieldtype": "Section Break"
  },
  {
   "default": "0.00",
   "fieldname": "total_rental",
   "fieldtype": "Currency",
   "label": "Total (incl. Tax)",
   "read_only": 1
  },
  {
   "default": "0.00",
   "depends_on": "eval:doc.deposit_received == 1",
   "fieldname": "deposit",
   "fieldtype": "Currency",
   "label": "Deposit",
   "mask": 1
  },
  {
   "default": "0",
   "fieldname": "deposit_received",
   "fieldtype": "Check",
   "label": "Deposit Received"
  },
  {
   "fieldname": "section_break_totals",
   "fieldtype": "Section Break"
  },
  {
   "default": "0.00",
   "fieldname": "tax",
   "fieldtype": "Currency",
   "label": "Tax",
   "read_only": 1
  },
  {
   "default": "0.00",
   "fieldname": "total_charges",
   "fieldtype": "Currency",
   "label": "Total Charges",
   "read_only": 1
  },
  {
   "depends_on": "eval:doc.status === 'cancelled'",
   "fieldname": "cancellation_fee",
   "fieldtype": "Currency",
   "label": "Cancellation Fee",
   "read_only": 1
  },
  {
   "description": "Add rate rows from Rate Schedule \u2014 each row auto-populates its rate when a Rate Type is selected.",
   "fieldname": "rate_lines",
   "fieldtype": "Table",
   "label": "Rates",
   "options": "Stay Rate Line"
  },
  {
   "fieldname": "guarantee_section",
   "fieldtype": "Section Break",
   "label": "Guarantee And Payment"
  },
  {
   "fieldname": "guarantee_type",
   "fieldtype": "Select",
   "label": "Guarantee Type",
   "options": "\nIndividual\nCompany\nDeposit\n6PM Courtesy Hold\nNo Guarantee"
  },
  {
   "fieldname": "payment_method",
   "fieldtype": "Select",
   "label": "Payment Method",
   "options": "\nCredit Card\nCash\nCheque\nDirect Bill"
  },
  {
   "fieldname": "column_break_guarantee",
   "fieldtype": "Column Break"
  },
  {
   "depends_on": "eval:['Credit Card'].includes(doc.payment_method)",
   "fieldname": "credit_card_type",
   "fieldtype": "Select",
   "label": "Card Type",
   "options": "\nVisa\nMastercard\nAmerican Express\nOther"
  },
  {
   "depends_on": "eval:['Credit Card'].includes(doc.payment_method)",
   "fieldname": "credit_card_last4",
   "fieldtype": "Data",
   "label": "Card Last 4 Digits"
  },
  {
   "depends_on": "eval:['Credit Card'].includes(doc.payment_method)",
   "fieldname": "card_expiry",
   "fieldtype": "Data",
   "label": "Card Expiry (MM/YY)"
  },
  {
   "fieldname": "requests_section",
   "fieldtype": "Section Break",
   "label": "Guest Requests"
  },
  {
   "fieldname": "special_requests",
   "fieldtype": "Text",
   "label": "Special Requests"
  },
  {
   "fieldname": "comments",
   "fieldtype": "Small Text",
   "label": "Comments"
  },
  {
   "fieldname": "column_break_requests",
   "fieldtype": "Column Break"
  },
  {
   "fieldname": "eta",
   "fieldtype": "Time",
   "label": "ETA (Estimated Arrival)"
  },
  {
   "default": "0",
   "fieldname": "turndown_requested",
   "fieldtype": "Check",
   "label": "Turndown Requested"
  },
  {
   "depends_on": "eval:doc.turndown_requested == 1",
   "fieldname": "turndown_reason",
   "fieldtype": "Small Text",
   "label": "Turndown Reason / Notes"
  },
  {
   "default": "0",
   "fieldname": "no_post",
   "fieldtype": "Check",
   "label": "No Post (block room charges)"
  },
  {
   "fieldname": "status_section",
   "fieldtype": "Section Break"
  },
  {
   "fieldname": "status",
   "fieldtype": "Select",
   "in_list_view": 1,
   "in_standard_filter": 1,
   "label": "Status",
   "options": "pending\nconfirmed\ncancelled"
  },
  {
   "fieldname": "color",
   "fieldtype": "Color",
   "label": "Calendar Color"
  },
  {
   "fieldname": "hotel_stay",
   "fieldtype": "Link",
   "label": "Check In Record",
   "options": "Checked In",
   "read_only": 1
  },
  {
   "fieldname": "column_break_status",
   "fieldtype": "Column Break"
  },
  {
   "depends_on": "eval:doc.status === 'cancelled'",
   "fieldname": "cancellation_reason",
   "fieldtype": "Select",
   "label": "Cancellation Reason",
   "mandatory_depends_on": "eval:doc.status === 'cancelled'",
   "options": "\nGuest Request\nNo Show\nDuplicate Booking\nRate Dispute\nOther"
  },
  {
   "fieldname": "cancellation_number",
   "fieldtype": "Data",
   "label": "Cancellation Number",
   "read_only": 1
  },
  {
   "fieldname": "proforma_invoice",
   "fieldtype": "Link",
   "label": "Proforma Invoice",
   "options": "Sales Invoice",
   "read_only": 1
  },
  {
   "fieldname": "guest_details_tab",
   "fieldtype": "Tab Break",
   "label": "Guest Details"
  },
  {
   "fieldname": "guest",
   "fieldtype": "Link",
   "in_list_view": 1,
   "label": "Guest Profile",
   "options": "Guest"
  },
  {
   "fieldname": "personal_details_section",
   "fieldtype": "Section Break",
   "label": "Personal Details"
  },
  {
   "fetch_from": "guest.guest_name",
   "fieldname": "full_name",
   "fieldtype": "Data",
   "label": "Full Name"
  },
  {
   "fieldname": "column_break_hzor",
   "fieldtype": "Column Break"
  },
  {
   "fetch_from": "guest.date_of_birth",
   "fieldname": "date_of_birth",
   "fieldtype": "Date",
   "label": "Date of Birth"
  },
  {
   "fieldname": "column_break_kshj",
   "fieldtype": "Column Break"
  },
  {
   "fieldname": "company",
   "fieldtype": "Data",
   "label": "Company"
  },
  {
   "fieldname": "contact_details_section",
   "fieldtype": "Section Break",
   "label": "Contact Details"
  },
  {
   "fetch_from": "guest.email",
   "fieldname": "email_address",
   "fieldtype": "Data",
   "label": "Email Address",
   "options": "Email"
  },
  {
   "fetch_from": "guest.city",
   "fieldname": "city",
   "fieldtype": "Data",
   "label": "City"
  },
  {
   "fieldname": "column_break_gcyq",
   "fieldtype": "Column Break"
  },
  {
   "fetch_from": "guest.phone",
   "fieldname": "phone_number",
   "fieldtype": "Phone",
   "label": "Phone Number"
  },
  {
   "fetch_from": "guest.state",
   "fieldname": "state",
   "fieldtype": "Data",
   "label": "State"
  },
  {
   "fieldname": "column_break_ulel",
   "fieldtype": "Column Break"
  },
  {
   "fetch_from": "guest.nationality",
   "fieldname": "country",
   "fieldtype": "Link",
   "label": "Country",
   "options": "Country"
  },
  {
   "fetch_from": "guest.postal_code",
   "fieldname": "postal_code",
   "fieldtype": "Data",
   "label": "Postal Code"
  },
  {
   "fieldname": "guarantee_and_payment_tab",
   "fieldtype": "Tab Break",
   "label": "Guarantee And Payment"
  },
  {
   "fieldname": "section_break_zons",
   "fieldtype": "Section Break"
  },
  {
   "fieldname": "column_break_walv",
   "fieldtype": "Column Break"
  },
  {
   "fieldname": "column_break_mvqd",
   "fieldtype": "Column Break"
  },
  {
   "fieldname": "section_break_ndhg",
   "fieldtype": "Section Break"
  },
  {
   "depends_on": "eval:['Direct Bill'].includes(doc.payment_method)",
   "fieldname": "customer_id",
   "fieldtype": "Link",
   "label": "Customer ID",
   "options": "Customer"
  },
  {
   "depends_on": "eval:['Cash'].includes(doc.payment_method)",
   "fieldname": "amount",
   "fieldtype": "Currency",
   "label": "Amount"
  },
  {
   "fieldname": "section_break_jmqu",
   "fieldtype": "Section Break"
  },
  {
   "fieldname": "column_break_imij",
   "fieldtype": "Column Break"
  },
  {
   "fetch_from": "guest.id_number",
   "fieldname": "id_number",
   "fieldtype": "Data",
   "label": "ID Number"
  },
  {
   "fetch_from": "guest.address_line_1",
   "fieldname": "address_line_1",
   "fieldtype": "Data",
   "label": "Address Line 1"
  },
  {
   "fetch_from": "guest.address_line_2",
   "fieldname": "address_line_2",
   "fieldtype": "Data",
   "label": "Address Line 2"
  },
  {
   "fetch_from": "guest.id_type",
   "fieldname": "guest_id_type",
   "fieldtype": "Select",
   "label": "Guest ID Type",
   "options": "\nPassport\nDriver License\nNational ID\nOther",
   "report_hide": 1
  },
  {
   "fieldname": "rate_details_tab",
   "fieldtype": "Tab Break",
   "label": "Rate Details"
  },
  {
   "fieldname": "column_break_rxah",
   "fieldtype": "Column Break"
  },
  {
   "fieldname": "section_break_amte",
   "fieldtype": "Section Break"
  },
  {
   "fieldname": "section_break_gufu",
   "fieldtype": "Section Break"
  },
  {
   "depends_on": "eval:['Cheque'].includes(doc.payment_method)",
   "fieldname": "cheque_number",
   "fieldtype": "Int",
   "label": "Cheque Number"
  },
  {
   "depends_on": "eval:['Cheque'].includes(doc.payment_method)",
   "fieldname": "cheque_amount",
   "fieldtype": "Currency",
   "label": "Cheque Amount"
  },
  {
   "depends_on": "eval:['Cheque'].includes(doc.payment_method)",
   "fieldname": "date_of_the_cheque",
   "fieldtype": "Date",
   "label": "Date of the Cheque"
  },
  {
   "depends_on": "eval:['Cheque'].includes(doc.payment_method)",
   "fetch_from": "guest.id_number",
   "fieldname": "guest_identification",
   "fieldtype": "Data",
   "label": "Guest Identification"
  },
  {
   "fieldname": "column_break_dtml",
   "fieldtype": "Column Break"
  },
  {
   "fieldname": "column_break_zcsq",
   "fieldtype": "Column Break"
  },
  {
   "depends_on": "eval:['Cheque'].includes(doc.payment_method)",
   "fieldname": "bank_name",
   "fieldtype": "Data",
   "label": "Bank Name"
  },
  {
   "depends_on": "eval:['Cheque'].includes(doc.payment_method)",
   "fieldname": "bank_account_no",
   "fieldtype": "Int",
   "label": "Bank Account No."
  },
  {
   "default": "0",
   "fieldname": "confirmation_email_sent",
   "fieldtype": "Check",
   "hidden": 1,
   "label": "Confirmation Email Sent"
  },
  {
   "fieldname": "amended_from",
   "fieldtype": "Link",
   "label": "Amended From",
   "no_copy": 1,
   "options": "Reservation",
   "print_hide": 1,
   "read_only": 1,
   "search_index": 1
  },
  {
   "fieldname": "column_break_ytyy",
   "fieldtype": "Column Break"
  },
  {
   "fieldname": "column_break_zbxj",
   "fieldtype": "Column Break"
  },
  {
   "fieldname": "column_break_saln",
   "fieldtype": "Column Break"
  },
  {
   "fieldname": "section_break_tnrc",
   "fieldtype": "Section Break"
  }
 ],
 "grid_page_length": 50,
 "index_web_pages_for_search": 1,
 "links": [],
 "modified": "2026-03-25 16:24:12.682457",
 "modified_by": "Administrator",
 "module": "iHotel",
 "name": "Reservation",
 "owner": "Administrator",
 "permissions": [
  {
   "create": 1,
   "delete": 1,
   "email": 1,
   "export": 1,
   "print": 1,
   "read": 1,
   "report": 1,
   "role": "System Manager",
   "share": 1,
   "write": 1
  },
  {
   "create": 1,
   "delete": 1,
   "email": 1,
   "export": 1,
   "print": 1,
   "read": 1,
   "report": 1,
   "role": "General Manager",
   "share": 1,
   "write": 1
  },
  {
   "create": 1,
   "email": 1,
   "export": 1,
   "print": 1,
   "read": 1,
   "report": 1,
   "role": "Front Desk Agent",
   "share": 1,
   "write": 1
  },
  {
   "export": 1,
   "read": 1,
   "report": 1,
   "role": "Revenue Manager"
  }
 ],
 "row_format": "Dynamic",
 "rows_threshold_for_grid_search": 20,
 "sort_field": "creation",
 "sort_order": "DESC",
 "states": [
 {
  "color": "Orange",
  "title": "pending"
 },
 {
  "color": "Green",
  "title": "confirmed"
 },
 {
  "color": "Red",
  "title": "cancelled"
 }
]
}
